cinder/__init__.py
cinder/context.py
cinder/coordination.py
cinder/exception.py
cinder/flow_utils.py
cinder/i18n.py
cinder/manager.py
cinder/opts.py
cinder/policy.py
cinder/quota.py
cinder/quota_utils.py
cinder/rpc.py
cinder/service.py
cinder/service_auth.py
cinder/ssh_utils.py
cinder/utils.py
cinder/version.py
cinder/api/__init__.py
cinder/api/api_utils.py
cinder/api/common.py
cinder/api/extensions.py
cinder/api/microversions.py
cinder/api/urlmap.py
cinder/api/versions.py
cinder/api/contrib/__init__.py
cinder/api/contrib/admin_actions.py
cinder/api/contrib/availability_zones.py
cinder/api/contrib/backups.py
cinder/api/contrib/capabilities.py
cinder/api/contrib/cgsnapshots.py
cinder/api/contrib/consistencygroups.py
cinder/api/contrib/extended_services.py
cinder/api/contrib/extended_snapshot_attributes.py
cinder/api/contrib/hosts.py
cinder/api/contrib/qos_specs_manage.py
cinder/api/contrib/quota_classes.py
cinder/api/contrib/quotas.py
cinder/api/contrib/resource_common_manage.py
cinder/api/contrib/scheduler_hints.py
cinder/api/contrib/scheduler_stats.py
cinder/api/contrib/services.py
cinder/api/contrib/snapshot_actions.py
cinder/api/contrib/snapshot_manage.py
cinder/api/contrib/snapshot_unmanage.py
cinder/api/contrib/types_extra_specs.py
cinder/api/contrib/types_manage.py
cinder/api/contrib/used_limits.py
cinder/api/contrib/volume_actions.py
cinder/api/contrib/volume_encryption_metadata.py
cinder/api/contrib/volume_host_attribute.py
cinder/api/contrib/volume_image_metadata.py
cinder/api/contrib/volume_manage.py
cinder/api/contrib/volume_mig_status_attribute.py
cinder/api/contrib/volume_tenant_attribute.py
cinder/api/contrib/volume_transfer.py
cinder/api/contrib/volume_type_access.py
cinder/api/contrib/volume_type_encryption.py
cinder/api/contrib/volume_unmanage.py
cinder/api/middleware/__init__.py
cinder/api/middleware/auth.py
cinder/api/middleware/fault.py
cinder/api/middleware/request_id.py
cinder/api/openstack/__init__.py
cinder-27.0.0.dist-info/AUTHORS
cinder-27.0.0.dist-info/LICENSE
cinder-27.0.0.dist-info/METADATA
cinder-27.0.0.dist-info/WHEEL
cinder-27.0.0.dist-info/entry_points.txt
cinder-27.0.0.dist-info/pbr.json
cinder-27.0.0.dist-info/top_level.txt
cinder-27.0.0.dist-info/RECORD
