Metadata-Version: 2.1
Name: cinder
Version: 27.0.0
Summary: OpenStack Block Storage
Home-page: https://docs.openstack.org/cinder/latest/
Author: OpenStack
Author-email: openstack-discuss@lists.openstack.org
Project-URL: Source, https://opendev.org/openstack/cinder
Project-URL: Tracker, https://bugs.launchpad.net/cinder
Classifier: Environment :: OpenStack
Classifier: Intended Audience :: Information Technology
Classifier: Intended Audience :: System Administrators
Classifier: License :: OSI Approved :: Apache Software License
Classifier: Operating System :: POSIX :: Linux
Classifier: Programming Language :: Python
Classifier: Programming Language :: Python :: Implementation :: CPython
Classifier: Programming Language :: Python :: 3 :: Only
Classifier: Programming Language :: Python :: 3
Classifier: Programming Language :: Python :: 3.10
Classifier: Programming Language :: Python :: 3.11
Classifier: Programming Language :: Python :: 3.12
Requires-Python: >=3.10
License-File: LICENSE
License-File: AUTHORS
Requires-Dist: pbr >=5.8.0
Requires-Dist: decorator >=4.4.2
Requires-Dist: eventlet !=0.32.0,>=0.30.1
Requires-Dist: greenlet >=0.4.16
Requires-Dist: iso8601 >=0.1.12
Requires-Dist: jsonschema >=3.2.0
Requires-Dist: keystoneauth1 >=4.2.1
Requires-Dist: keystonemiddleware >=9.1.0
Requires-Dist: lxml >=4.5.2
Requires-Dist: oslo.config >=8.3.2
Requires-Dist: oslo.concurrency >=4.5.0
Requires-Dist: oslo.context >=3.4.0
Requires-Dist: oslo.db >=11.0.0
Requires-Dist: oslo.log >=4.6.1
Requires-Dist: oslo.messaging >=14.6.0
Requires-Dist: oslo.middleware >=4.1.1
Requires-Dist: oslo.policy >=4.5.0
Requires-Dist: oslo.privsep >=2.6.2
Requires-Dist: oslo.reports >=3.2.0
Requires-Dist: oslo.rootwrap >=6.2.0
Requires-Dist: oslo.serialization >=4.2.0
Requires-Dist: oslo.service >=2.8.0
Requires-Dist: oslo.upgradecheck >=1.1.1
Requires-Dist: oslo.utils >=6.0.0
Requires-Dist: oslo.versionedobjects >=2.4.0
Requires-Dist: osprofiler >=3.4.0
Requires-Dist: packaging >=20.4
Requires-Dist: paramiko >=2.7.2
Requires-Dist: Paste >=3.4.3
Requires-Dist: PasteDeploy >=2.1.0
Requires-Dist: pyparsing >=2.4.7
Requires-Dist: python-barbicanclient >=5.0.1
Requires-Dist: python-glanceclient >=3.2.2
Requires-Dist: python-keystoneclient >=4.1.1
Requires-Dist: python-novaclient >=18.2.0
Requires-Dist: python-swiftclient >=3.10.1
Requires-Dist: requests >=2.25.1
Requires-Dist: Routes >=2.4.1
Requires-Dist: taskflow >=4.5.0
Requires-Dist: rtslib-fb >=2.1.74
Requires-Dist: SQLAlchemy >=1.4.23
Requires-Dist: stevedore >=3.2.2
Requires-Dist: tabulate >=0.8.7
Requires-Dist: tenacity >=6.3.1
Requires-Dist: WebOb >=1.8.6
Requires-Dist: oslo.i18n >=5.1.0
Requires-Dist: oslo.vmware >=3.10.0
Requires-Dist: os-brick >=6.10.0
Requires-Dist: os-win >=5.5.0
Requires-Dist: tooz >=2.8.0
Requires-Dist: google-api-python-client >=1.11.0
Requires-Dist: castellan >=3.7.0
Requires-Dist: cryptography >=3.1
Requires-Dist: cursive >=0.2.2
Requires-Dist: zstd >=1.4.5.1
Requires-Dist: boto3 >=1.18.49
Requires-Dist: distro >=1.8.0
Requires-Dist: tzdata >=2022.4
Provides-Extra: all
Requires-Dist: websocket-client >=1.3.2 ; extra == 'all'
Requires-Dist: pyOpenSSL >=17.5.0 ; extra == 'all'
Requires-Dist: storops >=0.5.10 ; extra == 'all'
Requires-Dist: pywbem >=0.7.0 ; extra == 'all'
Requires-Dist: python-3parclient >=4.2.10 ; extra == 'all'
Requires-Dist: krest >=1.3.0 ; extra == 'all'
Requires-Dist: infinisdk >=103.0.1 ; extra == 'all'
Requires-Dist: py-pure-client >=1.47.0 ; extra == 'all'
Requires-Dist: rsd-lib >=1.1.0 ; extra == 'all'
Requires-Dist: storpool >=7.1.0 ; extra == 'all'
Requires-Dist: storpool.spopenstack >=2.2.1 ; extra == 'all'
Requires-Dist: dfs-sdk >=1.2.25 ; extra == 'all'
Requires-Dist: rbd-iscsi-client >=0.1.8 ; extra == 'all'
Requires-Dist: python-linstor >=1.7.0 ; extra == 'all'
Requires-Dist: psutil >=5.7.2 ; extra == 'all'
Provides-Extra: datacore
Requires-Dist: websocket-client >=1.3.2 ; extra == 'datacore'
Provides-Extra: datera
Requires-Dist: dfs-sdk >=1.2.25 ; extra == 'datera'
Provides-Extra: ds8k
Requires-Dist: pyOpenSSL >=17.5.0 ; extra == 'ds8k'
Provides-Extra: fujitsu
Requires-Dist: pywbem >=0.7.0 ; extra == 'fujitsu'
Provides-Extra: hpe3par
Requires-Dist: python-3parclient >=4.2.10 ; extra == 'hpe3par'
Provides-Extra: infinidat
Requires-Dist: infinisdk >=103.0.1 ; extra == 'infinidat'
Provides-Extra: kaminario
Requires-Dist: krest >=1.3.0 ; extra == 'kaminario'
Provides-Extra: linstor
Requires-Dist: python-linstor >=1.7.0 ; extra == 'linstor'
Provides-Extra: powermax
Requires-Dist: pyOpenSSL >=17.5.0 ; extra == 'powermax'
Provides-Extra: pure
Requires-Dist: py-pure-client >=1.47.0 ; extra == 'pure'
Provides-Extra: quobyte
Requires-Dist: psutil >=5.7.2 ; extra == 'quobyte'
Provides-Extra: rbd_iscsi
Requires-Dist: rbd-iscsi-client >=0.1.8 ; extra == 'rbd_iscsi'
Provides-Extra: rsd
Requires-Dist: rsd-lib >=1.1.0 ; extra == 'rsd'
Provides-Extra: storpool
Requires-Dist: storpool >=7.1.0 ; extra == 'storpool'
Requires-Dist: storpool.spopenstack >=2.2.1 ; extra == 'storpool'
Provides-Extra: test
Requires-Dist: hacking <7.1.0,>=7.0.0 ; extra == 'test'
Requires-Dist: flake8-import-order <0.19.0 ; extra == 'test'
Requires-Dist: flake8-logging-format >=0.6.0 ; extra == 'test'
Requires-Dist: stestr >=3.2.1 ; extra == 'test'
Requires-Dist: coverage >=5.5 ; extra == 'test'
Requires-Dist: ddt >=1.4.4 ; extra == 'test'
Requires-Dist: fixtures >=3.0.0 ; extra == 'test'
Requires-Dist: oslotest >=4.5.0 ; extra == 'test'
Requires-Dist: PyMySQL >=0.10.0 ; extra == 'test'
Requires-Dist: psycopg2-binary >=2.8.5 ; extra == 'test'
Requires-Dist: SQLAlchemy-Utils >=0.37.8 ; extra == 'test'
Requires-Dist: testtools >=2.4.0 ; extra == 'test'
Requires-Dist: doc8 >=0.8.1 ; extra == 'test'
Requires-Dist: mypy <1.18.0,>=1.7.0 ; extra == 'test'
Requires-Dist: moto >=5.0.0 ; extra == 'test'
Requires-Dist: distro >=1.8.0 ; extra == 'test'
Provides-Extra: unity
Requires-Dist: storops >=0.5.10 ; extra == 'unity'
Provides-Extra: vnx
Requires-Dist: storops >=0.5.10 ; extra == 'vnx'
